fastclean/__init__.py
fastclean/build_templates.py
fastclean/cli_main.py
fastclean/main.py
fastclean/setup.py
fastclean/application/interfaces/__init__.py
fastclean/application/interfaces/file_system.py
fastclean/application/interfaces/template_engine.py
fastclean/application/interfaces/validator.py
fastclean/application/interfaces/add_feature/add_authentication.py
fastclean/application/interfaces/add_feature/add_caching.py
fastclean/application/interfaces/add_feature/add_monitoring.py
fastclean/application/interfaces/add_feature/dto.py
fastclean/application/interfaces/api/dependencyes.py
fastclean/application/interfaces/api/v1/routes/user.py
fastclean/application/interfaces/schemas/user.py
fastclean/application/use_cases/add_feature/__init__.py
fastclean/application/use_cases/create_project/__init__.py
fastclean/application/use_cases/create_project/create_project.py
fastclean/application/use_cases/create_project/dto.py
fastclean/application/use_cases/generate_crud/__init__.py
fastclean/application/use_cases/generate_crud/dto.py
fastclean/application/use_cases/generate_crud/generate_crud.py
fastclean/application/use_cases/user/create_user.py
fastclean/application/use_cases/user/get_user.py
fastclean/application/use_cases/user/list_user.py
fastclean/config/__init__.py
fastclean/config/constants.py
fastclean/config/settings.py
fastclean/core/use_case.py
fastclean/core/entities/__init__.py
fastclean/core/entities/base.py
fastclean/core/entities/project.py
fastclean/core/entities/template.py
fastclean/core/entities/user.py
fastclean/core/exceptions/__init__.py
fastclean/core/exceptions/base.py
fastclean/core/exceptions/validation.py
fastclean/core/value_objects/__init__.py
fastclean/core/value_objects/auth_type.py
fastclean/core/value_objects/cache_type.py
fastclean/core/value_objects/database_type.py
fastclean/core/value_objects/project_config.py
fastclean/infrastructure/config/settings.py
fastclean/infrastructure/database/database.py
fastapi_clean_cli-1.0.1.dist-info/METADATA
fastapi_clean_cli-1.0.1.dist-info/WHEEL
fastapi_clean_cli-1.0.1.dist-info/entry_points.txt
fastapi_clean_cli-1.0.1.dist-info/top_level.txt
fastapi_clean_cli-1.0.1.dist-info/RECORD
